solphedge/__init__.py
solphedge/solphege.py
solphedge/models/__init__.py
solphedge/models/deltalogS_FFNN_model.pkl
solphedge/models/deltalogS_features_novariance.json
solphedge/models/deltalogS_scaler.json
solphedge/models/neglogS_FFNN_model.pkl
solphedge/models/neglogS_features_novariance.json
solphedge/models/neglogS_scaler.json
solphedge-0.0.4.post3.dist-info/licenses/LICENSE
solphedge-0.0.4.post3.dist-info/METADATA
solphedge-0.0.4.post3.dist-info/WHEEL
solphedge-0.0.4.post3.dist-info/top_level.txt
solphedge-0.0.4.post3.dist-info/RECORD
