Metadata-Version: 2.4
Name: solphedge
Version: 0.0.4.post3
Summary: pH-dependent solubility predictions for small molecules
Home-page: https://github.com/OlivierBeq/solphedge
Author: Olivier J. M. Béquignon
Author-email: "olivier.bequignon.maintainer@gmail.com"
Maintainer: Olivier J. M. Béquignon
Maintainer-email: "olivier.bequignon.maintainer@gmail.com"
Keywords: pH-dependent solubility,cheminformatics,QSAR
Classifier: Development Status :: 5 - Production/Stable
Classifier: License :: OSI Approved :: MIT License
Classifier: Programming Language :: Python :: 3.12
Classifier: Programming Language :: Python :: 3.11
Requires-Python: >=3.11
License-File: LICENSE
Requires-Dist: bluedesc-pywrapper>=0.0.6.post1
Requires-Dist: cdk-pywrapper>=0.1.0
Requires-Dist: mold2-pywrapper>=0.1.0
Requires-Dist: padel-pywrapper>=1.0.5
Requires-Dist: chemopy2>=1.0.5
Requires-Dist: pandas
Requires-Dist: rdkit>=2024.3.1
Requires-Dist: scikit-learn>=1.4.0
Requires-Dist: papyrus_structure_pipeline>=0.0.5
Requires-Dist: numpy>=2.0.0
Provides-Extra: docs
Requires-Dist: sphinx; extra == "docs"
Requires-Dist: sphinx-rtd-theme; extra == "docs"
Requires-Dist: sphinx-autodoc-typehints; extra == "docs"
Provides-Extra: testing
Requires-Dist: pytest; extra == "testing"
Dynamic: license-file
